{
    "/assets/js/app.js": "/assets/js/app.js?id=5eb6e7b66c6c11f3d247",
    "/assets/css/main.css": "/assets/css/main.css?id=0d7a6c02f58af1931077",
    "/css/style.css": "/css/style.css?id=9c5c659ef1c3fab1b6b3",
    "/students/css/main.css": "/students/css/main.css?id=26963985bf174e6aff35",
    "/assets/js/login.js": "/assets/js/login.js?id=300049dd13b6bf162f78",
    "/js/theme.js": "/js/theme.js?id=a9aecc5fd60876e7b104",
    "/students/js/auth.js": "/students/js/auth.js?id=c5541a22ee752f12c0bd",
    "/students/js/nav.js": "/students/js/nav.js?id=d2177040c1b451d22106"
}
